query_summary/__init__.py
query_summary/counter.py
query_summary/middleware.py
query_summary-0.1.1.dist-info/LICENSE
query_summary-0.1.1.dist-info/METADATA
query_summary-0.1.1.dist-info/WHEEL
query_summary-0.1.1.dist-info/top_level.txt
query_summary-0.1.1.dist-info/RECORD
