Metadata-Version: 2.1
Name: query_summary
Version: 0.1.1
Summary: A Flask middleware to track MongoDB queries and provide query statistics.
Home-page: https://github.com/mstfsu/query_summary
Author: mstfsu
Author-email: su.mustafa@hotmail.com
Project-URL: Bug Tracker, https://github.com/mstfsu/query_summary/issues
Project-URL: Documentation, https://github.com/mstfsu/query_summary#readme
Project-URL: Source Code, https://github.com/mstfsu/query_summary
Classifier: Programming Language :: Python :: 3
Classifier: License :: OSI Approved :: MIT License
Classifier: Operating System :: OS Independent
Requires-Python: >=3.7
License-File: LICENSE
Requires-Dist: Flask>=2.0
Requires-Dist: pymongo>=4.0
Requires-Dist: mongoengine>=0.24.0
